pyalexs3/__init__.py
pyalexs3/core.py
pyalexs3/schemas.py
pyalexs3/py.typed
pyalexs3-0.1.4.dist-info/METADATA
pyalexs3-0.1.4.dist-info/WHEEL
pyalexs3-0.1.4.dist-info/licenses/LICENSE
pyalexs3-0.1.4.dist-info/RECORD
