Metadata-Version: 2.4
Name: pyalexs3
Version: 0.1.4
Summary: OpenAlex S3 processor
Project-URL: Homepage, https://github.com/EurekAI-Org/pyalexs3
Project-URL: Repository, https://github.com/EurekAI-Org/pyalexs3
Project-URL: Issues, https://github.com/EurekAI-Org/pyalexs3/issues
Author-email: Adityam Ghosh <adityam.ghosh@gmail.com>
License: MIT
License-File: LICENSE
Classifier: Development Status :: 3 - Alpha
Classifier: Intended Audience :: Science/Research
Classifier: License :: OSI Approved :: MIT License
Classifier: Operating System :: OS Independent
Classifier: Programming Language :: Python :: 3
Classifier: Programming Language :: Python :: 3 :: Only
Classifier: Programming Language :: Python :: 3.10
Classifier: Programming Language :: Python :: 3.11
Classifier: Programming Language :: Python :: 3.12
Classifier: Topic :: Scientific/Engineering :: Information Analysis
Classifier: Typing :: Typed
Requires-Python: >=3.10
Requires-Dist: boto3>=1.40.48
Requires-Dist: duckdb>=1.4.1
Requires-Dist: numpy>=2.2.6
Requires-Dist: pandas>=2.3.3
Requires-Dist: rich>=14.1.0
Provides-Extra: dev
Requires-Dist: black>=24.4.2; extra == 'dev'
Requires-Dist: boto3-stubs[s3]; extra == 'dev'
Requires-Dist: moto[s3]>=5; extra == 'dev'
Requires-Dist: mypy; extra == 'dev'
Requires-Dist: pytest; extra == 'dev'
Requires-Dist: pytest-cov; extra == 'dev'
Requires-Dist: ruff; extra == 'dev'
